DESCRIPTION.rst
MANIFEST.in
README.md
setup.py
geocluster/__init__.py
geocluster/geobound.py
geocluster/geoboundbase.py
geocluster/geocluster.py
geocluster/geoconvertion.py
geocluster/geopoint.py
geocluster.egg-info/PKG-INFO
geocluster.egg-info/SOURCES.txt
geocluster.egg-info/dependency_links.txt
geocluster.egg-info/top_level.txt