Metadata-Version: 1.1
Name: geocluster
Version: 1.0.0
Summary: GeoCluster is a framework agnostic library to help map clusterization
Home-page: UNKNOWN
Author: Régis FLORET
Author-email: regis@regisblog.fr
License: MIT
Keywords: Geocoding map cluster
Platform: UNKNOWN
Classifier: Development Status :: 5 - Production/Stable
Classifier: Intended Audience :: Developers
Classifier: License :: OSI Approved :: MIT License
Classifier: Operating System :: OS Independent
Classifier: Programming Language :: Python :: 2
Classifier: Programming Language :: Python :: 2.7
Classifier: Topic :: Scientific/Engineering :: Visualization
Classifier: Topic :: Software Development :: Libraries :: Python Modules
Classifier: Topic :: Software Development :: Localization
